mrsd/__init__.py
mrsd/adc.py
mrsd/diagram.py
mrsd/echo.py
mrsd/event.py
mrsd/gradient.py
mrsd/multi_gradient.py
mrsd/rf_pulse.py
mrsd-1.0.0.dist-info/LICENSE
mrsd-1.0.0.dist-info/METADATA
mrsd-1.0.0.dist-info/WHEEL
mrsd-1.0.0.dist-info/top_level.txt
mrsd-1.0.0.dist-info/RECORD
