Metadata-Version: 2.1
Name: mrsd
Version: 1.0.0
Summary: MR sequence diagram toolkit
Home-page: https://github.com/lamyj/mrsd
Author: Julien Lamy
Author-email: lamy@unistra.fr
License: MIT
Keywords: MRI,sequence,diagram,matplotlib
Platform: UNKNOWN
Classifier: Development Status :: 5 - Production/Stable
Classifier: Environment :: Console
Classifier: Framework :: Matplotlib
Classifier: Intended Audience :: Education
Classifier: Intended Audience :: Healthcare Industry
Classifier: Intended Audience :: Science/Research
Classifier: License :: OSI Approved :: MIT License
Classifier: Programming Language :: Python :: 3
Classifier: Topic :: Scientific/Engineering :: Medical Science Apps.
Classifier: Topic :: Scientific/Engineering :: Physics
Requires-Python: >=3.6
License-File: LICENSE
Requires-Dist: matplotlib (>=3.3)
Requires-Dist: numpy
